[
  {
    "id": "e9925925-4cc4-46aa-b01d-72a9fff88f0d",
    "data": [
      {
        "text": "I\u0027ll be back in a few minutes",
        "userDefined": false
      }
    ],
    "isTemplate": false,
    "count": 0,
    "lang": "en-us",
    "updated": 0
  },
  {
    "id": "959c6ec2-28ee-46c9-a45a-c0316ece5054",
    "data": [
      {
        "text": "be back ",
        "userDefined": false
      },
      {
        "text": "in",
        "userDefined": false
      },
      {
        "text": " ",
        "userDefined": false
      },
      {
        "text": "5",
        "userDefined": false
      },
      {
        "text": " minutes",
        "userDefined": false
      }
    ],
    "isTemplate": false,
    "count": 0,
    "lang": "en-us",
    "updated": 0
  },
  {
    "id": "b149a864-cd45-482b-b05a-69eac2794d14",
    "data": [
      {
        "text": "I\u0027ll get back to you ",
        "userDefined": false
      },
      {
        "text": "in",
        "userDefined": false
      },
      {
        "text": " a moment",
        "userDefined": false
      }
    ],
    "isTemplate": false,
    "count": 0,
    "lang": "en-us",
    "updated": 0
  },
  {
    "id": "7e3349e9-21e6-46bf-bf2d-b6eea472a7a8",
    "data": [
      {
        "text": "I\u0027ll be back",
        "userDefined": false
      }
    ],
    "isTemplate": false,
    "count": 0,
    "lang": "en-us",
    "updated": 0
  },
  {
    "id": "ed2be5c6-dc8d-42aa-b23b-5f2158b8f2ac",
    "data": [
      {
        "text": "I promise to ",
        "userDefined": false
      },
      {
        "text": "come",
        "userDefined": false
      },
      {
        "text": " back",
        "userDefined": false
      }
    ],
    "isTemplate": false,
    "count": 0,
    "lang": "en-us",
    "updated": 0
  }
]